attemp_requests/__init__.py
attemp_requests/attempts_requests.py
attemp_requests/unpack_payload_dict.py
utils/__init__.py
utils/logger_settings.py
attemptrequestslib-0.1.dist-info/METADATA
attemptrequestslib-0.1.dist-info/WHEEL
attemptrequestslib-0.1.dist-info/top_level.txt
attemptrequestslib-0.1.dist-info/RECORD
